tmn/__init__.py
tmn/configuration.py
tmn/display.py
tmn/elements/__init__.py
tmn/elements/network.py
tmn/elements/service.py
tmn/elements/volume.py
tmn/environments.py
tmn/tmn.py
tmn-0.5.12.dist-info/entry_points.txt
tmn-0.5.12.dist-info/WHEEL
tmn-0.5.12.dist-info/METADATA
tmn-0.5.12.dist-info/RECORD
